janus_api/__init__.py
janus_api/exceptions.py
janus_api/manager.py
janus_api/utils.py
janus_api/models/__init__.py
janus_api/models/base.py
janus_api/models/request.py
janus_api/models/response.py
janus_api/models/videoroom/__init__.py
janus_api/models/videoroom/fields.py
janus_api/models/videoroom/request.py
janus_api/models/videoroom/response.py
janus_api/plugins/__init__.py
janus_api/plugins/audiobridge.py
janus_api/plugins/base.py
janus_api/plugins/p2p.py
janus_api/plugins/sip.py
janus_api/plugins/streaming.py
janus_api/plugins/textroom.py
janus_api/plugins/videoroom.py
janus_api/session/__init__.py
janus_api/session/base.py
janus_api/session/websocket.py
janus_api/transport/__init__.py
janus_api/transport/websocket.py
janus_api/types/__init__.py
janus_api-0.1.3.dist-info/METADATA
janus_api-0.1.3.dist-info/WHEEL
janus_api-0.1.3.dist-info/top_level.txt
janus_api-0.1.3.dist-info/RECORD
