Metadata-Version: 2.4
Name: janus-api
Version: 0.1.3
Summary: Python bindings for Janus webrtc Media Server
Author-email: Leydotpy <leydotpy.dev@gmail.com>
Requires-Python: >=3.14
Requires-Dist: asgiref>=3.10.0
Requires-Dist: httpx>=0.28.1
Requires-Dist: pydantic>=2.12.4
Requires-Dist: pyee>=13.0.0
Requires-Dist: python-decouple>=3.8
Requires-Dist: reactivex>=4.1.0
Requires-Dist: redis>=7.0.1
Requires-Dist: websockets>=15.0.1
